streamwee/__init__.py
streamwee/py.typed
streamwee-0.0.0.dist-info/METADATA
streamwee-0.0.0.dist-info/WHEEL
streamwee-0.0.0.dist-info/licenses/LICENSE
streamwee-0.0.0.dist-info/RECORD
