Metadata-Version: 2.1
Name: streamwee
Version: 0.0.0
Summary: Animate, fast and easy
Project-URL: Documentation, https://ahuang11.github.io/streamwee/
Project-URL: Source, https://github.com/ahuang11/streamwee
Author-email: streamwee <hey.at.py@gmail.com>
License-File: LICENSE
Classifier: Programming Language :: Python :: 3 :: Only
Requires-Python: >=3.9
